<?xml version="1.0" encoding="UTF-8"?>
<dc>
<title>NOAA&apos;s Ocean Service Office of Response and Restoration</title>
<identifier>http://eot.us.archive.org/eot08/20080916005358/response.restoration.noaa.gov/</identifier>
<provenance>http://response.restoration.noaa.gov/</provenance>
<date>2008-09-16</date>
<date>2009-08-26</date>
<description></description>
<subject>Coastal Protection</subject>
<subject>Coral Reefs</subject>
<subject>CPRD</subject>
<subject>DAC</subject>
<subject>Damage Assessment</subject>
<subject>DARRP</subject>
<subject>Hazmat</subject>
<subject>HMRD</subject>
<subject>Pribilof Islands</subject>
<subject>Pribilof Project Office</subject>
<subject>NOAA</subject>
<subject>NOS</subject>
<subject>Response and Restoration</subject>
<subject>incident news</subject>
<subject>IncidentNews</subject>
<subject>Unified Command</subject>
<subject>oil spill response</subject>
<subject>U.S. Coast Guard</subject>
<subject>USCG</subject>
<subject>On Scene Coordinator</subject>
<subject>responsible party</subject>
<subject>Katrina</subject>
<subject>hurricane</subject>
<subject>database</subject>
<subject>maps</subject>
<subject>query manager</subject>
<subject>qm</subject>
<subject>marplot</subject>
<subject>watershed</subject>
<subject>arcview</subject>
<subject>arcmap</subject>
<subject>arcgis</subject>
<subject>ims</subject>
<subject>order</subject>
<subject>cprd</subject>
<subject>san francisco</subject>
<subject>calcasieu</subject>
<subject>hudson river</subject>
<subject>st. lawrence</subject>
<subject>portland harbor</subject>
<subject>anacostia</subject>
<subject>vieques</subject>
<subject>christina river</subject>
<subject>charles river</subject>
<subject>elizabeth river Kalamazoo River</subject>
<subject>Newark Bay</subject>
<subject>Puget Sound</subject>
<subject>Sheboygan River</subject>
<subject>Southern California</subject>
<subject>St. John River</subject>
<subject>St. Louis</subject>
<subject>Portland Harbor</subject>
<subject>Willamette River</subject>
<subject>Vieques</subject>
<subject>Delaware</subject>
<subject>FOSC guidebook</subject>
<subject>NOAA Guidebook</subject>
<subject>NOAA Handbook</subject>
<subject>SST Guidebook</subject>
<subject>NOAA scientific support</subject>
<subject>scientific support coordinator</subject>
<subject>SSC</subject>
<subject>Incident Command System</subject>
<subject>ICS</subject>
<subject>oil spill response</subject>
<subject>CAMEO Chemicals</subject>
<subject>chemical database</subject>
<subject>CAMEO software suite</subject>
<subject>CAMEO programs</subject>
<subject>NOAA CAMEO</subject>
<subject>NOAA ALOHA</subject>
<subject>NOAA MARPLOT</subject>
<subject>CAMEO ALOHA MARPLOT</subject>
<subject>CAMEO MARPLOT ALOHA</subject>
<subject>ALOHA CAMEO MARPLOT</subject>
<subject>ALOHA MARPLOT CAMEO</subject>
<subject>MARPLOT ALOHA CAMEO</subject>
<subject>MARPLOT CAMEO ALOHA</subject>
<subject>chemical emergency management software</subject>
<subject>chemical accidents</subject>
<subject>CAMEO suite</subject>
<subject>CAMEO software</subject>
<subject>emergency responses</subject>
<subject>emergency planning</subject>
<subject>hazmat software</subject>
<subject>hazmat programs</subject>
<subject>chemical spills</subject>
<subject>hazmat spills</subject>
<subject>hazardous materials spills</subject>
<subject>chemical responses</subject>
<subject>hazmat responses</subject>
<subject>hazmat responders</subject>
<subject>first responders</subject>
<subject>emergency responders</subject>
<subject>Coastal Response Research Center</subject>
<subject>CRRC</subject>
<subject>University of New Hampshire</subject>
<subject>UNH</subject>
<subject>oil spill response</subject>
<subject>oil spill research</subject>
<subject>oil spill restoration</subject>
<subject>DARP</subject>
<subject>DARRP</subject>
<subject>Exxon Valdez</subject>
<subject>oil spill</subject>
<subject>assessment</subject>
<subject>restoration</subject>
<subject>hazardous waste site</subject>
<subject>vessel groundings</subject>
<subject>Dispersant Mission Planner 2</subject>
<subject>DMP2</subject>
<subject>DMP 2</subject>
<subject>DMP II</subject>
<subject>dispersants</subject>
<subject>Spill Tools</subject>
<subject>ICS forms</subject>
<subject>Incident Command System forms</subject>
<subject>oil spill response</subject>
<subject>ESI Mapping</subject>
<subject>ESI maps</subject>
<subject>Environmental Sensitivity Index Mapping</subject>
<subject>Environmental Sensitivity Index maps</subject>
<subject>sensitivity mapping</subject>
<subject>cleanup strategies</subject>
<subject>NOAA ESI data</subject>
<subject>oiled birds</subject>
<subject>oiled animals</subject>
<subject>oil spill response</subject>
<subject>oil spill planning</subject>
<subject>oiled shorelines</subject>
<subject>oiled beaches</subject>
<subject>resource maps</subject>
<subject>resource mapping</subject>
<subject>sensitivity maps</subject>
<subject>ESI GIS data  </subject>
<subject>Exxon Valdez oil spill</subject>
<subject>Exon Valdez oil spill</subject>
<subject>Alaska oil spills</subject>
<subject>Bligh Reef</subject>
<subject>Prince William Sound oil spills</subject>
<subject>Mearns Rock</subject>
<subject>major oil spills</subject>
<subject>biggest oil spills</subject>
<subject>cleanup Exxon Valdez</subject>
<subject>oil spills in the ocean</subject>
<subject>Exxon Valdez pictures</subject>
<subject>Exxon Valdez oil spill pictures</subject>
<subject>pictures of oil spills</subject>
<subject>ecosystem recovery Exxon Valdez</subject>
<subject>oil spill responses</subject>
<subject>exxon valdez photos</subject>
<subject>exon valdez photos</subject>
<subject>Exxon Valdez oil spill photos</subject>
<subject>largest oil spills</subject>
<subject>restoration</subject>
<subject>portal</subject>
<subject>restoration tools</subject>
<subject>sea turtles</subject>
<subject>oil spill response</subject>
<subject>oil spill planning</subject>
<subject>guidance document</subject>
<subject>protect</subject>
<subject>restore</subject>
<subject>reef ecosystems</subject>
<subject>economic factors</subject>
<subject>fishing</subject>
<subject>coastal development</subject>
<subject>pollution</subject>
<subject>protection</subject>
<subject>coral</subject>
<subject>coral reefs</subject>
<subject>planning</subject>
<subject>response</subject>
<subject>spill response</subject>
<subject>Vieques</subject>
<subject>Puerto Rico</subject>
<subject>Restoration</subject>
<subject>Caribbean</subject>
<subject>history</subject>
<subject>Office of Response and Restoration</subject>
<subject>ORR</subject>
<subject>OR&amp;R</subject>
<subject>HAZMAT</subject>
<subject>pribilof islands</subject>
<subject>st. paul island</subject>
<subject>st. george island</subject>
<subject>remediation</subject>
<subject>restoration</subject>
<subject>managing seafood safety</subject>
<subject>assessing seafood exposure</subject>
<subject>seafood contamination</subject>
<subject>risk assessment</subject>
<subject>seafood monitoring</subject>
<subject>oil spill</subject>
<subject>taint</subject>
<subject>guidance</subject>
<subject>sensory testing standard procedures</subject>
<subject>sensory evaluation</subject>
<subject>petroleum taint</subject>
<subject>GNOME</subject>
<subject>oil spill trajectory modeling</subject>
<subject>oil spills</subject>
<subject>oil spill response</subject>
<subject>NOAA oil spill model</subject>
<subject>spill response software</subject>
<subject>oil spill software</subject>
<subject>training</subject>
<subject>oil spill response</subject>
<subject>chemical spill response</subject>
<subject>chemical accident</subject>
<subject>spill planning</subject>
<subject>Science of Oil Spills Workshops</subject>
<subject>Science of Oil Spills classes</subject>
<subject>SOS classes</subject>
<subject>SOS workshops</subject>
<subject>SOS courses</subject>
<subject>Environmental Spill Response Workshops</subject>
<subject>ESR Workshops </subject>
<subject>Barge DM932</subject>
<subject>Tintomara</subject>
<subject>New Orleans oil spill</subject>
<subject>Mississippi oil spill</subject>
<subject>mothball fleet</subject>
<subject>Suisun Bay</subject>
<subject>reserve fleet</subject>
<subject>pcbs</subject>
<subject>tbt</subject>
<type>web site</type>
<format>text</format>
<coverage>Executive</coverage>
<source>response</source>
<source>restoration</source>
<source>noaa</source>
<relation>http://crawls.archive.org/collections/eot08/</relation>
</dc>
